susu/__init__.py
susu/__main__.py
susu/_version.py
susu/main.py
susu-0.1.0.dist-info/licenses/LICENSE
susu-0.1.0.dist-info/licenses/NOTICE
susu-0.1.0.dist-info/METADATA
susu-0.1.0.dist-info/WHEEL
susu-0.1.0.dist-info/entry_points.txt
susu-0.1.0.dist-info/top_level.txt
susu-0.1.0.dist-info/RECORD
